LICENSE.txt
README.md
setup.py
rocket_yacine/__init__.py
rocket_yacine/rocket.py
rocket_yacine.egg-info/PKG-INFO
rocket_yacine.egg-info/SOURCES.txt
rocket_yacine.egg-info/dependency_links.txt
rocket_yacine.egg-info/requires.txt
rocket_yacine.egg-info/top_level.txt