Metadata-Version: 2.1
Name: rocket_yacine
Version: 1.0.0
Summary: An awesome package that does something
Home-page: http://pypi.python.org/pypi/<rocket_yacine>/
Author: <DAIT DEHANE YACINE>
Author-email: <y.daitdehane@esi-sba.dz>
License: LICENSE.txt
License-File: LICENSE.txt
Requires-Dist: rocket_yacine
